sync_yt/__init__.py
sync_yt/__main__.py
sync_yt/sync_yt.py
sync_yt-1.1.0.dist-info/licenses/LICENSE
sync_yt-1.1.0.dist-info/METADATA
sync_yt-1.1.0.dist-info/WHEEL
sync_yt-1.1.0.dist-info/entry_points.txt
sync_yt-1.1.0.dist-info/top_level.txt
sync_yt-1.1.0.dist-info/RECORD
