Metadata-Version: 2.4
Name: sync-yt
Version: 1.1.0
Summary: CLI tool to mirror YouTube playlists into local directories
Author-email: Siddhesh Dharme <siddheshdharme18@gmail.com>
License-Expression: MIT
Project-URL: Homepage, https://pypi.org/project/sync-yt/
Project-URL: Repository, https://github.com/sidtronics/sync-yt
Project-URL: Issues, https://github.com/sidtronics/sync-yt/issues
Keywords: yt-dlp,youtube,playlist,sync,downloader,music,videos,cli
Classifier: Development Status :: 4 - Beta
Classifier: Environment :: Console
Classifier: Intended Audience :: End Users/Desktop
Classifier: Natural Language :: English
Classifier: Operating System :: OS Independent
Classifier: Programming Language :: Python :: 3.10
Classifier: Topic :: System :: Archiving :: Backup
Classifier: Topic :: Internet
Classifier: Topic :: Multimedia :: Sound/Audio
Classifier: Topic :: Multimedia :: Video
Requires-Python: >=3.10
License-File: LICENSE
Requires-Dist: yt-dlp
Dynamic: license-file
